globox/__init__.py
globox/__main__.py
globox/annotation.py
globox/annotationset.py
globox/atomic.py
globox/boundingbox.py
globox/cli.py
globox/errors.py
globox/evaluation.py
globox/file_utils.py
globox/image_utils.py
globox/thread_utils.py
globox/utils.py
globox-2.8.0.dist-info/METADATA
globox-2.8.0.dist-info/WHEEL
globox-2.8.0.dist-info/entry_points.txt
globox-2.8.0.dist-info/licenses/LICENSE.txt
globox-2.8.0.dist-info/RECORD
