Metadata-Version: 2.4
Name: globox
Version: 2.8.0
Summary: Globox is a package and command line interface to read and convert object detection databases (COCO, YOLO, PascalVOC, LabelMe, CVAT, OpenImage, ...) and evaluate them with COCO and PascalVOC.
Project-URL: Homepage, https://github.com/laclouis5/globox
Project-URL: Repository, https://github.com/laclouis5/globox
Project-URL: Documentation, https://github.com/laclouis5/globox/#readme
Project-URL: Issues, https://github.com/laclouis5/globox/issues
Author-email: Louis Lac <lac.louis5@gmail.com>
Maintainer-email: Louis Lac <lac.louis5@gmail.com>
License-File: LICENSE.txt
Keywords: annotation,average precision,bounding boxes,coco,cvat,mean average precision,metrics,object detection,openimages,pascal voc,yolo
Classifier: License :: OSI Approved :: MIT License
Classifier: Operating System :: OS Independent
Classifier: Programming Language :: Python :: 3 :: Only
Classifier: Programming Language :: Python :: 3.9
Classifier: Programming Language :: Python :: 3.10
Classifier: Programming Language :: Python :: 3.11
Classifier: Programming Language :: Python :: 3.12
Classifier: Programming Language :: Python :: Implementation :: CPython
Classifier: Topic :: Scientific/Engineering
Classifier: Topic :: Scientific/Engineering :: Artificial Intelligence
Requires-Python: >=3.9
Requires-Dist: numpy>=1.26
Requires-Dist: rich>=13.3
Requires-Dist: tqdm>=4.65
